<DataSource ID="ListGridField" autoIdField="name">
	<fields>
        <field name="type"              type="ListGridFieldType" rebuildOnChange="true" xmlAttribute="true" basic="true"/>
		<field name="name"				type="string" basic="true" xmlAttribute="true"/>

        <!-- ID auto-generated by VB -->
        <field name="autoName" xmlAttribute="true" type="string" hidden="true"/>

		<field name="title" 			type="string" basic="true" xmlAttribute="true"/>
        <field name="showTitle"         type="boolean" />
		<field name="summaryTitle" 	type="string"/>
        <field name="width" 			type="number" xmlAttribute="true"/>
        <field name="maxWidth" 			type="number" xmlAttribute="true"/>
        <field name="minWidth" 			type="number" xmlAttribute="true"/>
		<field name="align" 			type="alignEnum" xmlAttribute="true" basic="true" />
        <field name="cellAlign"         type="alignEnum"/>
        <field name="wrap"              type="boolean"/>
        <field name="baseStyle"         type="cssClass"/>
        <field name="headerBaseStyle"         type="cssClass"/>
        <field name="headerTitleStyle"         type="cssClass"/>
        <field name="hidden"            type="boolean" title="Hide Initially" xmlAttribute="true"/>
        <!-- showIf is hidden in VB because "hidden" property above makes more sense -->
        <field name="showIf"            type="string" editorType="checkbox" hidden="true" />
        <field name="hideOnPhone"       type="boolean" basic="true" />
        <field name="hideOnTablet"      type="boolean" basic="true" />
        <field name="showHover"         type="boolean" basic="true" />
		<field name="valueMap" 			type="ValueMap"/>
        <field name="cellIcon" type="URL" editorType="ImageChooserItem" basic="true"/>
        <field name="icon"  type="string" basic="true"/>
        <field name="iconSize"  type="number"/>
        <field name="iconWidth"  type="number"/>
        <field name="iconHeight"  type="number"/>
        <field name="editorIconHeight" type="number"/>
        <field name="editorIconWidth" type="number"/>
        <field name="iconOrientation"  type="string"/>
        <field name="iconSpacing"  type="number"/>
        <field name="showDisabledIcon"  type="boolean"/>
        <field name="showRollOverIcon"  type="boolean"/>
        <field name="showFocusedIcon" type="boolean"/>
        <field name="showDownIcon"  type="boolean"/>
        <field name="showSelectedIcon"  type="boolean"/>
        <field name="valueIcons"        type="ValueMap"/>
        
        <field name="editorImageURLPrefix" type="URL"/>
        <field name="editorImageURLSuffix" type="URL"/>   
        <field name="icons" type="FormItemIcon" multiple="true"/>
        <field name="defaultValue" fieldTypeProperty="type"      type="any"/>
        <field name="iconVAlign" type="alignEnum"/>
        <field name="defaultIconSrc" type="URL"/>
        
        <field name="imageSize" type="number"/>
        <field name="imageHeight" type="number"/>
        <field name="imageWidth" type="number"/>
        <field name="valueIconWidth" type="number"/>
        <field name="valueIconHeight" type="number"/>
        <field name="valueIconSize" type="number"/>
        <field name="valueIconLeftPadding" type="number"/>
        <field name="valueIconRightPadding" type="number"/>
        <field name="valueIconOrientation" type="enum">
            <valueMap>
                <value>left</value>
                <value>right</value>
            </valueMap>
        </field>
        <field name="editorValueIcons"        type="ValueMap"/>
        <field name="editorValueIconWidth" type="number"/>
        <field name="editorValueIconHeight" type="number"/>
        <field name="imageURLPrefix" type="string"/>
        <field name="imageURLSuffix" type="string"/>
        <field name="showValueIconOnly" type="boolean"/>
        <field name="suppressValueIcon" type="boolean"/>
        <field name="hiliteIconSize" type="number"/>
        <field name="hiliteIconWidth" type="number"/>
        <field name="hiliteIconHeight" type="number"/>
        <field name="hiliteIconLeftPadding" type="number"/>
        <field name="hiliteIconRightPadding" type="number"/>
        <field name="hiliteIconPosition" type="enum">
            <valueMap>
                <value>before</value>
                <value>after</value>
                <value>replace</value>
            </valueMap>
        </field> 
        
        <field name="optionDataSource"  type="string" basic="true" />
        <field name="valueField"        type="string" requiresDSField="optionDataSource"/>
        <field name="displayField"      type="string" requiresDSField="optionDataSource"/>
        <field name="optionCriteria"    type="AdvancedCriteria" requiresDSField="optionDataSource"/>

        <field name="displayFormat"     type="string"/>
        <field name="inputFormat"       type="string"/>
        <field name="initialValue" fieldTypeProperty="type"      type="any"/>

        <field name="editorValueMap"    type="ValueMap"/>
		<field name="canSort" 			type="boolean" basic="true" showNullAsTrue="true"/>
		<field name="emptyCellValue" 	type="HTMLString"/>
		<field name="sortDirection" 	type="sortEnum"/>
        <field name="sortByDisplayField" type="boolean"/>
        <field name="sortByMappedValue" type="boolean"/>
		<field name="canEdit" 			type="boolean" basic="true" showNullAsTrue="true"/>
        <field name="canToggle"         type="boolean" basic="true" />
        <field name="validateOnChange"  type="boolean" />
		<field name="required" 			type="boolean"/>
		<field name="validators"		type="Validator"	multiple="true"	title="Validators"/>
        <field name="nextTabColNum"     type="boolean" visibility="advancedInlineEdit"/>
        <field name="previousTabColNum" type="boolean" visibility="advancedInlineEdit"/>
        <field name="enterKeyEditAction" type="enum">
            <valueMap>
				<value>done</value>
				<value>nextCell</value>
				<value>nextRow</value>
				<value>nextRowStart</value>
			</valueMap>
		</field>	
		<field name="escapeKeyEditAction" type="enum">
            <valueMap>
                <value>cancel</value>
                <value>done</value>
            </valueMap>
        </field>
        <field name="editorType"        type="className" />
        <field name="editorProperties"  type="FormItem" propertiesOnly="true"/>
        <field name="linkText"          type="text"/>
        <field name="canFilter"         type="boolean" basic="true" showNullAsTrue="true" />
        <field name="frozen"            type="boolean" basic="true" />

        <field name="defaultFilterValue" fieldTypeProperty="type" type="any"/>
        <field name="filterOnKeypress"  type="boolean"/>
        <field name="filterEditorValueMap" type="object" />
        <field name="filterEditorType"  type="className" />
        <field name="filterEditorProperties" type="ListGrid"/>
        
        <field name="canEditFormula" type="boolean" showNullAsTrue="true"/>
        <field name="canEditSummary" type="boolean" showNullAsTrue="true"/>
        <field name="canGroupBy" type="boolean" showNullAsTrue="true"/>
        <field name="groupPrecision" type="number"/>
        <field name="groupGranularity" type="number"/>
        <field name="canSortClientOnly" type="boolean"/>
        <field name="autoFetchDisplayMap" type="boolean"/>

        <field name="editorFormula" type="UserFormula" useRuleScope="true"/>
        <field name="editorTextFormula" type="UserSummary" useRuleScope="true"/>
 
        <field name="userFormula" type="UserFormula" useRuleScope="true"/>
        <field name="userSummary" type="UserSummary" useRuleScope="true"/>

        <field name="canExport" type="boolean" basic="true" showNullAsTrue="true" />
 
        <field name="cellPrompt" type="HTMLString" basic="true" />
 
	</fields>
    
    <types>
        <type ID="ListGridFieldType" inheritsFrom="enum">
            <valueMap>
                <value ID="text">text: a normal text value</value>
                <value ID="integer">integer: a whole number</value>
                <value ID="float">float: a fractional or decimal number</value>
                <value ID="boolean">boolean: only a true or false allowed</value>
                <value ID="date">date: a specific date, with no time</value>
                <value ID="time">time: a specific time, with no date</value>
                <value ID="datetime">datetime: a specific time on a specific date</value>
                <value ID="sequence">sequence: a number where every new record gets a new value automatically</value>
                <value ID="URL">URL: a link to something on the web</value>
                <value ID="image">image: a link to an image on the web</value>
                <value ID="imageFile">imageFile: an image stored in this DataSource</value>
                <value ID="binary">binary: any binary file that is not an image</value>
                <value ID="icon">icon: a field that renders just an icon, that users can click to perform an action</value>
            </valueMap>
        </type>
    </types>

    <methods>
        <method name="recordClick" basic="true" />
    </methods>
</DataSource>
